{
    "result": {
        
        "menu1_name": "除皱瘦脸",
        "product_info": [
            {
                "pid": "15517",
                "spu_id": "15448",
                "product_type": "2",
                "hospital_id": "8841",
                "total_cnt": "101",
                "sold_cnt": "2",
                "title": "【除皱瘦脸】除皱瘦脸除皱！原装进口除皱瘦脸！正品保障！尊贵享受奢华除皱！",
                "each_cnt": "1",
                "calendar_cnt": "4",
                "show_calendar_cnt": "30",
                "avg_score": "5.0",
                "marketing_language": "",
                "is_vip": "1",
                "is_vip_user": 0,
                "close_yn": "0",
                "display_yn": "1",
                "order_auto_cnt": "471",
                "order_cnt": 562,
                "price_online": "2580",
                "price_deposit": "516",
                "price_origin": "5160",
                "paystages_notice": "首付预约金，尾款分期付：¥184.9 ×12期",
                "paystages_notice_android": "首付预约金，尾款分期付：<font color='#F57397'>¥184.9</font> ×12期",
                "wei_kuan_yn": 1,
                "wei_kuan": [
                    "10减10",
                    "10减10",
                    "10减10"
                ],
                "wei_kuan_list": [
                    "付尾款，最高立减¥10",
                    "付尾款，最高立减¥10",
                    "付尾款，最高立减¥10"
                ],
                "is_pin_tuan_yn": 0,
                "tuan": {},
                "pin_tuan": [],
                "ori_on_sale_start_date": 1574128800,
                "ori_on_sale_end_date": 1574733600,
                "on_sale_flag": "1",
                "vip_user_on_sale": "0",
                "last_cnt_type": 1,
                "purchlimit_yn": 1,
                "purchlimit_type": "1",
                "on_sale_start_date": 1574128800,
                "on_sale_end_date": 1574733600,
                "purchlimit_endtime": 1574733600,
                "purchlimit_text": "活动结束后恢复¥5160，仅剩99个",
                "vip_cut": 77,
                "vip_price_online": "2503",
                "vip_price_deposit": "439",
                "new_user_discount_price": 0,
                "new_user_discount_rate": 0,
                "new_user_text": "",
                "new_user_text_show_yn": 0,
                "price_cut": 2580,
                "img_cover": {
                    "ident": "lnimage",
                    "w": "100",
                    "h": "100",
                    "u": "https://img2.soyoung.com/post/20191113/8/a15c8c68e42e97fbd1555bdac09c0dfc_400.png"
                },
                "gong_yn": "0",
                "bao_xian_yn": 0,
                "sole": "0",
                "security": "0",
                "tj_order": "0",
                "hospital_name": "北京首玺丽格医疗美容诊所",
                "country": "2",
                "district_1": "1",
                "district_2": "1",
                "institution_type": "1",
                "paystages_notice_new": "首付预约金，尾款分期付：¥184.9 ×12期",
                "paystages_notice_android_new": "首付预约金，尾款分期付：<font color='#F57397'>¥184.9</font> ×12期",
                "subtitle": "原装进口保妥适",
                "product_icon_yn": 0,
                "product_icon": "",
                "doctor": [
                    {
                        "doctor_id": "154567",
                        "name_cn": "谌燃",
                        "paystages": "0"
                    }
                ],
                "doctor_name": "谌燃",
                "give_product_yn": 0,
                "yuyue_standard_str": "发起预约",
                "juli": ""
            },
            {
                "pid": "452903",
                "spu_id": "418665",
                "product_type": "2",
                "hospital_id": "24688",
                "total_cnt": 0,
                "sold_cnt": "44",
                "title": "【除皱瘦脸】保妥适 除皱瘦脸 100单位 ，【BOTOX瘦脸】保妥适BOTOX 注射瘦脸100单位 下颌缘提升 打造小v脸",
                "each_cnt": 0,
                "calendar_cnt": "1",
                "show_calendar_cnt": "13",
                "avg_score": "5.0",
                "marketing_language": "",
                "is_vip": "1",
                "is_vip_user": 0,
                "close_yn": "0",
                "display_yn": "1",
                "order_auto_cnt": "1255",
                "order_cnt": 1339,
                "price_online": "2980",
                "price_deposit": "596",
                "price_origin": "4258",
                "paystages_notice": "",
                "paystages_notice_android": "",
                "wei_kuan_yn": 1,
                "wei_kuan": [
                    "1999减100",
                    "599减50"
                ],
                "wei_kuan_list": [
                    "付尾款，最高立减¥100",
                    "付尾款，最高立减¥50"
                ],
                "is_pin_tuan_yn": 0,
                "tuan": {},
                "pin_tuan": [],
                "ori_on_sale_start_date": -62170012800,
                "ori_on_sale_end_date": -62170012800,
                "on_sale_flag": "0",
                "vip_user_on_sale": 0,
                "vip_cut": 89,
                "vip_price_online": "2891",
                "vip_price_deposit": "507",
                "new_user_discount_price": 0,
                "new_user_discount_rate": 0,
                "new_user_text": "",
                "new_user_text_show_yn": 0,
                "price_cut": 0,
                "img_cover": {
                    "ident": "lnimage",
                    "w": "100",
                    "h": "100",
                    "u": "https://img2.soyoung.com/post/20190822/8/ec092b92d1f18bb2106678a9b4fc8da2_400.png"
                },
                "gong_yn": "0",
                "bao_xian_yn": 0,
                "sole": "0",
                "security": "0",
                "tj_order": "0",
                "hospital_name": "北京京城皮肤美容医院",
                "country": "2",
                "district_1": "1",
                "district_2": "1",
                "institution_type": "1",
                "subtitle": "",
                "product_icon_yn": 0,
                "product_icon": "",
                "doctor": [
                    {
                        "doctor_id": "73396",
                        "name_cn": "闫爱萍",
                        "paystages": "0"
                    }
                ],
                "doctor_name": "闫爱萍",
                "give_product_yn": 0,
                "yuyue_standard_str": "发起预约",
                "juli": ""
            },
            {
                "pid": "485058",
                "spu_id": "444604",
                "product_type": "2",
                "hospital_id": "22313",
                "total_cnt": 0,
                "sold_cnt": "63",
                "title": "【除皱瘦脸】保妥适 除皱瘦脸 50单位 ，除皱瘦脸●BOTOX瘦脸针50U 正品可验证 进口品质效果好●美如画中人",
                "each_cnt": 0,
                "calendar_cnt": "15",
                "show_calendar_cnt": "30",
                "avg_score": "4.7",
                "marketing_language": "",
                "is_vip": "1",
                "is_vip_user": 0,
                "close_yn": "0",
                "display_yn": "1",
                "order_auto_cnt": "416",
                "order_cnt": 476,
                "price_online": "1880",
                "price_deposit": "376",
                "price_origin": "4800",
                "paystages_notice": "首付预约金，尾款分期付：¥134.73 ×12期",
                "paystages_notice_android": "首付预约金，尾款分期付：<font color='#F57397'>¥134.73</font> ×12期",
                "wei_kuan_yn": 1,
                "wei_kuan": [
                    "1500减200",
                    "1500减200",
                    "1000减100",
                    "500减50"
                ],
                "wei_kuan_list": [
                    "付尾款，最高立减¥200",
                    "付尾款，最高立减¥200",
                    "付尾款，最高立减¥100",
                    "付尾款，最高立减¥50"
                ],
                "is_pin_tuan_yn": 0,
                "tuan": {},
                "pin_tuan": [],
                "ori_on_sale_start_date": -62170012800,
                "ori_on_sale_end_date": -62170012800,
                "on_sale_flag": "0",
                "vip_user_on_sale": 0,
                "vip_cut": 56,
                "vip_price_online": "1824",
                "vip_price_deposit": "320",
                "new_user_discount_price": 0,
                "new_user_discount_rate": 0,
                "new_user_text": "",
                "new_user_text_show_yn": 0,
                "price_cut": 0,
                "img_cover": {
                    "ident": "lnimage",
                    "w": "100",
                    "h": "100",
                    "u": "https://img2.soyoung.com/post/20191119/0/f8f3ab5d6524d84355bd79d7b2972803_400.png"
                },
                "gong_yn": "0",
                "bao_xian_yn": 0,
                "sole": "0",
                "security": "0",
                "tj_order": "0",
                "hospital_name": "北京画美医疗美容医院（原长虹整形）",
                "country": "2",
                "district_1": "1",
                "district_2": "1",
                "institution_type": "1",
                "paystages_notice_new": "首付预约金，尾款分期付：¥134.73 ×12期",
                "paystages_notice_android_new": "首付预约金，尾款分期付：<font color='#F57397'>¥134.73</font> ×12期",
                "subtitle": "正品认证 支持验货",
                "product_icon_yn": 0,
                "product_icon": "",
                "doctor": [
                    {
                        "doctor_id": "153778",
                        "name_cn": "张晓旭",
                        "paystages": "0"
                    },
                    {
                        "doctor_id": "155677",
                        "name_cn": "杨瑞锋",
                        "paystages": "0"
                    }
                ],
                "doctor_name": "张晓旭",
                "give_product_yn": 0,
                "yuyue_standard_str": "发起预约",
                "juli": ""
            },
            {
                "pid": "32014",
                "spu_id": "30454",
                "product_type": "2",
                "hospital_id": "8841",
                "total_cnt": "101",
                "sold_cnt": "2",
                "title": "【除皱瘦脸】【除皱瘦脸】【瘦腿&瘦肩二选一】正品可验！香肩美腿2选1，小香肩、漫画腿",
                "each_cnt": "1",
                "calendar_cnt": "3",
                "show_calendar_cnt": "30",
                "avg_score": "5.0",
                "marketing_language": "",
                "is_vip": "1",
                "is_vip_user": 0,
                "close_yn": "0",
                "display_yn": "1",
                "order_auto_cnt": "435",
                "order_cnt": 527,
                "price_online": "1568",
                "price_deposit": "314",
                "price_origin": "3136",
                "paystages_notice": "首付预约金，尾款分期付：¥112.33 ×12期",
                "paystages_notice_android": "首付预约金，尾款分期付：<font color='#F57397'>¥112.33</font> ×12期",
                "wei_kuan_yn": 1,
                "wei_kuan": [
                    "10减10",
                    "10减10",
                    "10减10"
                ],
                "wei_kuan_list": [
                    "付尾款，最高立减¥10",
                    "付尾款，最高立减¥10",
                    "付尾款，最高立减¥10"
                ],
                "is_pin_tuan_yn": 0,
                "tuan": {},
                "pin_tuan": [],
                "ori_on_sale_start_date": 1574128800,
                "ori_on_sale_end_date": 1574733600,
                "on_sale_flag": "1",
                "vip_user_on_sale": "0",
                "last_cnt_type": 1,
                "purchlimit_yn": 1,
                "purchlimit_type": "1",
                "on_sale_start_date": 1574128800,
                "on_sale_end_date": 1574733600,
                "purchlimit_endtime": 1574733600,
                "purchlimit_text": "活动结束后恢复¥3136，仅剩99个",
                "vip_cut": 47,
                "vip_price_online": "1521",
                "vip_price_deposit": "267",
                "new_user_discount_price": 0,
                "new_user_discount_rate": 0,
                "new_user_text": "",
                "new_user_text_show_yn": 0,
                "price_cut": 1568,
                "img_cover": {
                    "ident": "lnimage",
                    "w": "100",
                    "h": "100",
                    "u": "https://img2.soyoung.com/post/20191113/2/be882e04aa54f507418ed5112479a92d_400.png"
                },
                "gong_yn": "0",
                "bao_xian_yn": 0,
                "sole": "0",
                "security": "0",
                "tj_order": "0",
                "hospital_name": "北京首玺丽格医疗美容诊所",
                "country": "2",
                "district_1": "1",
                "district_2": "1",
                "institution_type": "1",
                "paystages_notice_new": "首付预约金，尾款分期付：¥112.33 ×12期",
                "paystages_notice_android_new": "首付预约金，尾款分期付：<font color='#F57397'>¥112.33</font> ×12期",
                "subtitle": "瘦腿 瘦肩 热门产品",
                "product_icon_yn": 0,
                "product_icon": "",
                "doctor": [
                    {
                        "doctor_id": "154567",
                        "name_cn": "谌燃",
                        "paystages": "0"
                    },
                    {
                        "doctor_id": "70246",
                        "name_cn": "沈波",
                        "paystages": "0"
                    }
                ],
                "doctor_name": "谌燃",
                "give_product_yn": 0,
                "yuyue_standard_str": "发起预约",
                "juli": ""
            },
            {
                "pid": "581497",
                "spu_id": "525614",
                "product_type": "2",
                "hospital_id": "108720",
                "total_cnt": 0,
                "sold_cnt": "0",
                "title": "【除皱瘦脸】保妥适 除皱瘦脸 100单位 ，保妥适瘦脸针+V脸提升 botox瘦脸针 V脸塑形 专家注射 正品足量",
                "each_cnt": 0,
                "calendar_cnt": "0",
                "show_calendar_cnt": "4",
                "avg_score": "0.0",
                "marketing_language": "",
                "is_vip": "1",
                "is_vip_user": 0,
                "close_yn": "0",
                "display_yn": "1",
                "order_auto_cnt": "52",
                "order_cnt": 52,
                "price_online": "3680",
                "price_deposit": "736",
                "price_origin": "9880",
                "paystages_notice": "",
                "paystages_notice_android": "",
                "wei_kuan_yn": 1,
                "wei_kuan": [
                    "1800减99",
                    "100减5"
                ],
                "wei_kuan_list": [
                    "付尾款，最高立减¥99",
                    "付尾款，最高立减¥5"
                ],
                "is_pin_tuan_yn": 0,
                "tuan": {},
                "pin_tuan": [],
                "ori_on_sale_start_date": -62170012800,
                "ori_on_sale_end_date": -62170012800,
                "on_sale_flag": "0",
                "vip_user_on_sale": 0,
                "vip_cut": 110,
                "vip_price_online": "3570",
                "vip_price_deposit": "626",
                "new_user_discount_price": 0,
                "new_user_discount_rate": 0,
                "new_user_text": "",
                "new_user_text_show_yn": 0,
                "price_cut": 0,
                "img_cover": {
                    "ident": "lnimage",
                    "w": "100",
                    "h": "100",
                    "u": "https://img2.soyoung.com/post/20191115/1/51aea11a67e9717ab1154e5a0921910b_400.png"
                },
                "gong_yn": "0",
                "bao_xian_yn": 0,
                "sole": "0",
                "security": "0",
                "tj_order": "0",
                "hospital_name": "北京小芙医疗美容",
                "country": "2",
                "district_1": "1",
                "district_2": "1",
                "institution_type": "1",
                "subtitle": "",
                "doctor": [
                    {
                        "doctor_id": "157958",
                        "name_cn": "戎新清",
                        "paystages": "0"
                    }
                ],
                "doctor_name": "戎新清",
                "give_product_yn": 0,
                "yuyue_standard_str": "发起预约",
                "juli": ""
            },
            {
                "pid": "570951",
                "spu_id": "468283",
                "product_type": "2",
                "hospital_id": "107982",
                "total_cnt": "55",
                "sold_cnt": "0",
                "title": "【除皱瘦脸】保妥适 除皱瘦脸 30单位 ，【私信享799元】保妥适除皱针  •公立三甲医师团•正品可验轻松祛除动态皱纹祛皱",
                "each_cnt": "1",
                "calendar_cnt": "0",
                "show_calendar_cnt": "30",
                "avg_score": "5.0",
                "marketing_language": "",
                "is_vip": "1",
                "is_vip_user": 0,
                "close_yn": "0",
                "display_yn": "1",
                "order_auto_cnt": "82",
                "order_cnt": 86,
                "price_online": "799",
                "price_deposit": "160",
                "price_origin": "1599",
                "paystages_notice": "首付预约金，尾款分期付：¥57.24 ×12期",
                "paystages_notice_android": "首付预约金，尾款分期付：<font color='#F57397'>¥57.24</font> ×12期",
                "wei_kuan_yn": 1,
                "wei_kuan": [
                    "511减51",
                    "110减11"
                ],
                "wei_kuan_list": [
                    "付尾款，最高立减¥51",
                    "付尾款，最高立减¥11"
                ],
                "is_pin_tuan_yn": 0,
                "tuan": {},
                "pin_tuan": [],
                "ori_on_sale_start_date": 1574391600,
                "ori_on_sale_end_date": 1574820000,
                "on_sale_flag": "1",
                "vip_user_on_sale": "0",
                "last_cnt_type": 1,
                "purchlimit_yn": 1,
                "purchlimit_type": "1",
                "on_sale_start_date": 1574391600,
                "on_sale_end_date": 1574820000,
                "purchlimit_endtime": 1574820000,
                "purchlimit_text": "活动结束后恢复¥1599，仅剩55个",
                "vip_cut": 24,
                "vip_price_online": "775",
                "vip_price_deposit": "136",
                "new_user_discount_price": 0,
                "new_user_discount_rate": 0,
                "new_user_text": "",
                "new_user_text_show_yn": 0,
                "price_cut": 800,
                "img_cover": {
                    "ident": "lnimage",
                    "w": "100",
                    "h": "100",
                    "u": "https://img2.soyoung.com/post/20191029/2/3ad80ee08d6401f2473bcf8fb39d4eff_400.png"
                },
                "gong_yn": "0",
                "bao_xian_yn": 0,
                "sole": "0",
                "security": "0",
                "tj_order": "0",
                "hospital_name": "北京德美诊联（中关村旗舰院)",
                "country": "2",
                "district_1": "1",
                "district_2": "1",
                "institution_type": "1",
                "paystages_notice_new": "首付预约金，尾款分期付：¥57.24 ×12期",
                "paystages_notice_android_new": "首付预约金，尾款分期付：<font color='#F57397'>¥57.24</font> ×12期",
                "subtitle": "抚平皱纹 立显年轻",
                "product_icon_yn": 0,
                "product_icon": "",
                "doctor": [
                    {
                        "doctor_id": "154312",
                        "name_cn": "杨璐",
                        "paystages": "0"
                    },
                    {
                        "doctor_id": "158667",
                        "name_cn": "卜虹森",
                        "paystages": "0"
                    }
                ],
                "doctor_name": "杨璐",
                "give_product_yn": 0,
                "yuyue_standard_str": "发起预约",
                "juli": ""
            },
            {
                "pid": "557172",
                "spu_id": "482510",
                "product_type": "2",
                "hospital_id": "104720",
                "total_cnt": 0,
                "sold_cnt": "3",
                "title": "【除皱瘦脸】保妥适 除皱瘦脸 100单位 ，进口瘦脸针下颌缘/V脸提升 二选一 无注射费 专业医生注射  做个小脸蛋的小仙女",
                "each_cnt": 0,
                "calendar_cnt": "0",
                "show_calendar_cnt": "30",
                "avg_score": "4.9",
                "marketing_language": "",
                "is_vip": "1",
                "is_vip_user": 0,
                "close_yn": "0",
                "display_yn": "1",
                "order_auto_cnt": "12",
                "order_cnt": 15,
                "price_online": "2980",
                "price_deposit": "596",
                "price_origin": "8800",
                "paystages_notice": "首付预约金，尾款分期付：¥213.56 ×12期",
                "paystages_notice_android": "首付预约金，尾款分期付：<font color='#F57397'>¥213.56</font> ×12期",
                "wei_kuan_yn": 1,
                "wei_kuan": [
                    "2000减200",
                    "1500减150",
                    "1200减492",
                    "1200减120",
                    "900减90",
                    "600减60",
                    "300减30"
                ],
                "wei_kuan_list": [
                    "付尾款，最高立减¥200",
                    "付尾款，最高立减¥150",
                    "付尾款，最高立减¥492",
                    "付尾款，最高立减¥120",
                    "付尾款，最高立减¥90",
                    "付尾款，最高立减¥60",
                    "付尾款，最高立减¥30"
                ],
                "is_pin_tuan_yn": 0,
                "tuan": {},
                "pin_tuan": [],
                "ori_on_sale_start_date": -62170012800,
                "ori_on_sale_end_date": -62170012800,
                "on_sale_flag": "0",
                "vip_user_on_sale": 0,
                "vip_cut": 89,
                "vip_price_online": "2891",
                "vip_price_deposit": "507",
                "new_user_discount_price": 0,
                "new_user_discount_rate": 0,
                "new_user_text": "",
                "new_user_text_show_yn": 0,
                "price_cut": 0,
                "img_cover": {
                    "ident": "lnimage",
                    "w": "100",
                    "h": "100",
                    "u": "https://img2.soyoung.com/post/20190920/8/1f31595c984fb4c9944ec053f1bb7add_400.png"
                },
                "gong_yn": "0",
                "bao_xian_yn": 0,
                "sole": "0",
                "security": "0",
                "tj_order": "0",
                "hospital_name": "北京卓新华星医疗美容",
                "country": "2",
                "district_1": "1",
                "district_2": "1",
                "institution_type": "1",
                "paystages_notice_new": "首付预约金，尾款分期付：¥213.56 ×12期",
                "paystages_notice_android_new": "首付预约金，尾款分期付：<font color='#F57397'>¥213.56</font> ×12期",
                "subtitle": "",
                "doctor": [
                    {
                        "doctor_id": "141709",
                        "name_cn": "姬广翰",
                        "paystages": "0"
                    }
                ],
                "doctor_name": "姬广翰",
                "give_product_yn": 0,
                "yuyue_standard_str": "发起预约",
                "juli": ""
            },
            {
                "pid": "30763",
                "spu_id": "29282",
                "product_type": "2",
                "hospital_id": "658",
                "total_cnt": 0,
                "sold_cnt": "108",
                "title": "【除皱瘦脸】衡力瘦腿瘦肩针 200单位足量 正品当场验证 多点定位 秒变铅笔腿 女神标配",
                "each_cnt": 0,
                "calendar_cnt": "4",
                "show_calendar_cnt": "21",
                "avg_score": "5.0",
                "marketing_language": "",
                "is_vip": "1",
                "is_vip_user": 0,
                "close_yn": "0",
                "display_yn": "1",
                "order_auto_cnt": "610",
                "order_cnt": 1911,
                "price_online": "1680",
                "price_deposit": "336",
                "price_origin": "8800",
                "paystages_notice": "首付预约金，尾款分期付：¥120.4 ×12期",
                "paystages_notice_android": "首付预约金，尾款分期付：<font color='#F57397'>¥120.4</font> ×12期",
                "wei_kuan_yn": 1,
                "wei_kuan": [
                    "800减50",
                    "200减10"
                ],
                "wei_kuan_list": [
                    "付尾款，最高立减¥50",
                    "付尾款，最高立减¥10"
                ],
                "is_pin_tuan_yn": 0,
                "tuan": {
                    "product_tuan_id": "21404",
                    "pid": "30763",
                    "tuan_status_old": "1",
                    "tuan_status": 3,
                    "tuan_app_status": 0,
                    "product_tuan_price": "2580",
                    "product_tuan_price_deposit": "516",
                    "product_tuan_price_hospital": 2064,
                    "tuan_surplus_num": 0,
                    "tuan_product_cnt": "2",
                    "tuan_start_date": "2018-06-21 11:00:00",
                    "tuan_end_date": "2018-06-22 10:59:59",
                    "tuan_last_time": 0,
                    "tuan_product_num": "50",
                    "tuan_product_num_onsale": "50",
                    "tuan_mount": "1",
                    "product_tuan_time": "172800",
                    "tuan_topic_id": "0"
                },
                "pin_tuan": [],
                "ori_on_sale_start_date": -62170012800,
                "ori_on_sale_end_date": -62170012800,
                "on_sale_flag": "0",
                "vip_user_on_sale": 0,
                "vip_cut": 50,
                "vip_price_online": "1630",
                "vip_price_deposit": "286",
                "new_user_discount_price": 0,
                "new_user_discount_rate": 0,
                "new_user_text": "",
                "new_user_text_show_yn": 0,
                "price_cut": 0,
                "img_cover": {
                    "ident": "lnimage",
                    "w": "100",
                    "h": "100",
                    "u": "https://img2.soyoung.com/post/20191112/8/d480b31f5808a16e7c80fa967949ae82_400.png"
                },
                "gong_yn": "0",
                "bao_xian_yn": 0,
                "sole": "0",
                "security": "0",
                "tj_order": "0",
                "hospital_name": "北京爱悦丽格医疗美容",
                "country": "2",
                "district_1": "1",
                "district_2": "1",
                "institution_type": "1",
                "paystages_notice_new": "首付预约金，尾款分期付：¥120.4 ×12期",
                "paystages_notice_android_new": "首付预约金，尾款分期付：<font color='#F57397'>¥120.4</font> ×12期",
                "subtitle": "月销量2000+",
                "product_icon_yn": 0,
                "product_icon": "",
                "doctor": [
                    {
                        "doctor_id": "154427",
                        "name_cn": "JOYOUNGHYUN  赵映贤 ",
                        "paystages": "0"
                    }
                ],
                "doctor_name": "JOYOUNGHYUN  赵映贤 ",
                "give_product_yn": 0,
                "yuyue_standard_str": "发起预约",
                "juli": ""
            },
            {
                "pid": "296477",
                "spu_id": "285893",
                "product_type": "2",
                "hospital_id": "104028",
                "total_cnt": "9",
                "sold_cnt": "3",
                "title": "【除皱瘦脸】衡力 除皱瘦脸 200单位 ，【私信享1580元】【瘦腿针/瘦肩针 200单位】正品保证  还你S型身材",
                "each_cnt": "1",
                "calendar_cnt": "10",
                "show_calendar_cnt": "30",
                "avg_score": "4.1",
                "marketing_language": "",
                "is_vip": "1",
                "is_vip_user": 0,
                "close_yn": "0",
                "display_yn": "1",
                "order_auto_cnt": "1072",
                "order_cnt": 2203,
                "price_online": "1580",
                "price_deposit": "316",
                "price_origin": "3199",
                "paystages_notice": "首付预约金，尾款分期付：¥113.23 ×12期",
                "paystages_notice_android": "首付预约金，尾款分期付：<font color='#F57397'>¥113.23</font> ×12期",
                "wei_kuan_yn": 1,
                "wei_kuan": [
                    "1111减111",
                    "511减51",
                    "110减11"
                ],
                "wei_kuan_list": [
                    "付尾款，最高立减¥111",
                    "付尾款，最高立减¥51",
                    "付尾款，最高立减¥11"
                ],
                "is_pin_tuan_yn": 0,
                "tuan": {},
                "pin_tuan": [],
                "ori_on_sale_start_date": 1574128800,
                "ori_on_sale_end_date": 1574733600,
                "on_sale_flag": "1",
                "vip_user_on_sale": "0",
                "last_cnt_type": 1,
                "purchlimit_yn": 1,
                "purchlimit_type": "1",
                "on_sale_start_date": 1574128800,
                "on_sale_end_date": 1574733600,
                "purchlimit_endtime": 1574733600,
                "purchlimit_text": "活动结束后恢复¥3199，仅剩6个",
                "vip_cut": 47,
                "vip_price_online": "1533",
                "vip_price_deposit": "269",
                "new_user_discount_price": 0,
                "new_user_discount_rate": 0,
                "new_user_text": "",
                "new_user_text_show_yn": 0,
                "price_cut": 1619,
                "img_cover": {
                    "ident": "lnimage",
                    "w": "100",
                    "h": "100",
                    "u": "https://img2.soyoung.com/post/20191105/4/83de54143a8370f6e07d8b0e1b773dc7_400.png"
                },
                "gong_yn": "0",
                "bao_xian_yn": 0,
                "sole": "0",
                "security": "0",
                "tj_order": "0",
                "hospital_name": "北京德美诊联",
                "country": "2",
                "district_1": "1",
                "district_2": "1",
                "institution_type": "1",
                "paystages_notice_new": "首付预约金，尾款分期付：¥113.23 ×12期",
                "paystages_notice_android_new": "首付预约金，尾款分期付：<font color='#F57397'>¥113.23</font> ×12期",
                "subtitle": "",
                "doctor": [
                    {
                        "doctor_id": "143189",
                        "name_cn": "MYOYUNJUNG",
                        "paystages": "0"
                    }
                ],
                "doctor_name": "MYOYUNJUNG",
                "give_product_yn": 0,
                "yuyue_standard_str": "发起预约",
                "juli": ""
            },
            {
                "pid": "580669",
                "spu_id": "524927",
                "product_type": "2",
                "hospital_id": "108110",
                "total_cnt": 0,
                "sold_cnt": "0",
                "title": "【除皱瘦脸】衡力 除皱瘦脸 200单位 ，衡力瘦肩针200U 官方认证注射医院 支持当面验证 免注射费",
                "each_cnt": 0,
                "calendar_cnt": "0",
                "show_calendar_cnt": "2",
                "avg_score": "0.0",
                "marketing_language": "",
                "is_vip": "1",
                "is_vip_user": 0,
                "close_yn": "0",
                "display_yn": "1",
                "order_auto_cnt": "68",
                "order_cnt": 68,
                "price_online": "3000",
                "price_deposit": "600",
                "price_origin": "4000",
                "paystages_notice": "",
                "paystages_notice_android": "",
                "wei_kuan_yn": 0,
                "wei_kuan": [],
                "wei_kuan_list": [],
                "is_pin_tuan_yn": 0,
                "tuan": {},
                "pin_tuan": [],
                "ori_on_sale_start_date": -62170012800,
                "ori_on_sale_end_date": -62170012800,
                "on_sale_flag": "0",
                "vip_user_on_sale": 0,
                "vip_cut": 90,
                "vip_price_online": "2910",
                "vip_price_deposit": "510",
                "new_user_discount_price": 0,
                "new_user_discount_rate": 0,
                "new_user_text": "",
                "new_user_text_show_yn": 0,
                "price_cut": 0,
                "img_cover": {
                    "ident": "lnimage",
                    "w": "100",
                    "h": "100",
                    "u": "https://img2.soyoung.com/post/20191113/9/50e62d435d88441170facfa66dea3bf1_400.png"
                },
                "gong_yn": "0",
                "bao_xian_yn": 0,
                "sole": "0",
                "security": "0",
                "tj_order": "0",
                "hospital_name": "北京塑研医疗美容诊所",
                "country": "2",
                "district_1": "1",
                "district_2": "1",
                "institution_type": "1",
                "subtitle": "",
                "doctor": [
                    {
                        "doctor_id": "157938",
                        "name_cn": "祁慧敏",
                        "paystages": "0"
                    },
                    {
                        "doctor_id": "157948",
                        "name_cn": "齐慧颉",
                        "paystages": "0"
                    }
                ],
                "doctor_name": "祁慧敏",
                "give_product_yn": 0,
                "yuyue_standard_str": "发起预约",
                "juli": ""
            },
            {
                "pid": "100750",
                "spu_id": "98070",
                "product_type": "2",
                "hospital_id": "66",
                "total_cnt": "20",
                "sold_cnt": "1",
                "title": "【除皱瘦脸】【北京美莱】保妥适瘦脸针 明星御用小脸秘籍，精致V脸套餐",
                "each_cnt": "0",
                "calendar_cnt": "10",
                "show_calendar_cnt": "21",
                "avg_score": "4.3",
                "marketing_language": "",
                "is_vip": "1",
                "is_vip_user": 0,
                "close_yn": "0",
                "display_yn": "1",
                "order_auto_cnt": "1104",
                "order_cnt": 3083,
                "price_online": "3000",
                "price_deposit": "600",
                "price_origin": "4285",
                "paystages_notice": "首付预约金，尾款分期付：¥215 ×12期",
                "paystages_notice_android": "首付预约金，尾款分期付：<font color='#F57397'>¥215</font> ×12期",
                "wei_kuan_yn": 1,
                "wei_kuan": [
                    "2000减200",
                    "1999减200",
                    "1000减100",
                    "101减100"
                ],
                "wei_kuan_list": [
                    "付尾款，最高立减¥200",
                    "付尾款，最高立减¥200",
                    "付尾款，最高立减¥100",
                    "付尾款，最高立减¥100"
                ],
                "is_pin_tuan_yn": 0,
                "tuan": {},
                "pin_tuan": [],
                "ori_on_sale_start_date": 1574391600,
                "ori_on_sale_end_date": 1574820000,
                "on_sale_flag": "1",
                "vip_user_on_sale": "0",
                "last_cnt_type": 1,
                "purchlimit_yn": 1,
                "purchlimit_type": "1",
                "on_sale_start_date": 1574391600,
                "on_sale_end_date": 1574820000,
                "purchlimit_endtime": 1574820000,
                "purchlimit_text": "活动结束后恢复¥4285，仅剩19个",
                "vip_cut": 90,
                "vip_price_online": "2910",
                "vip_price_deposit": "510",
                "new_user_discount_price": 0,
                "new_user_discount_rate": 0,
                "new_user_text": "",
                "new_user_text_show_yn": 0,
                "price_cut": 1285,
                "img_cover": {
                    "ident": "lnimage",
                    "w": "100",
                    "h": "100",
                    "u": "https://img2.soyoung.com/post/20191119/3/f68d73006e6386f17cf016a2fb73d0d7_400.png"
                },
                "gong_yn": "0",
                "bao_xian_yn": 0,
                "sole": "0",
                "security": "0",
                "tj_order": "0",
                "hospital_name": "北京美莱医疗美容",
                "country": "2",
                "district_1": "1",
                "district_2": "1",
                "institution_type": "1",
                "paystages_notice_new": "首付预约金，尾款分期付：¥215 ×12期",
                "paystages_notice_android_new": "首付预约金，尾款分期付：<font color='#F57397'>¥215</font> ×12期",
                "subtitle": "",
                "product_icon_yn": 0,
                "product_icon": "",
                "doctor": [
                    {
                        "doctor_id": "81278",
                        "name_cn": "戴琴",
                        "paystages": "0"
                    },
                    {
                        "doctor_id": "146261",
                        "name_cn": "宋长绪",
                        "paystages": "0"
                    }
                ],
                "doctor_name": "戴琴",
                "give_product_yn": 0,
                "yuyue_standard_str": "发起预约",
                "juli": ""
            },
            {
                "pid": "171256",
                "spu_id": "167528",
                "product_type": "2",
                "hospital_id": "28289",
                "total_cnt": 0,
                "sold_cnt": "928",
                "title": "【除皱瘦脸】【国产瘦腿针/瘦肩针】 保质保量 香肩美腿 柔美曲线 ",
                "each_cnt": 0,
                "calendar_cnt": "17",
                "show_calendar_cnt": "23",
                "avg_score": "4.7",
                "marketing_language": "",
                "is_vip": "1",
                "is_vip_user": 0,
                "close_yn": "0",
                "display_yn": "1",
                "order_auto_cnt": "932",
                "order_cnt": 1882,
                "price_online": "1780",
                "price_deposit": "356",
                "price_origin": "6800",
                "paystages_notice": "",
                "paystages_notice_android": "",
                "wei_kuan_yn": 0,
                "wei_kuan": [],
                "wei_kuan_list": [],
                "is_pin_tuan_yn": 0,
                "tuan": {},
                "pin_tuan": [],
                "ori_on_sale_start_date": -62170012800,
                "ori_on_sale_end_date": -62170012800,
                "on_sale_flag": "0",
                "vip_user_on_sale": 0,
                "vip_cut": 53,
                "vip_price_online": "1727",
                "vip_price_deposit": "303",
                "new_user_discount_price": 0,
                "new_user_discount_rate": 0,
                "new_user_text": "",
                "new_user_text_show_yn": 0,
                "price_cut": 0,
                "img_cover": {
                    "ident": "lnimage",
                    "w": "100",
                    "h": "100",
                    "u": "https://img2.soyoung.com/post/20190924/7/f900c5653a99604e5c64e710dd703f13_400.png"
                },
                "gong_yn": "0",
                "bao_xian_yn": 0,
                "sole": "0",
                "security": "0",
                "tj_order": "0",
                "hospital_name": "北京联合丽格第一医疗美容医院",
                "country": "2",
                "district_1": "1",
                "district_2": "1",
                "institution_type": "1",
                "subtitle": "",
                "doctor": [
                    {
                        "doctor_id": "144692",
                        "name_cn": "尚薇薇",
                        "paystages": "0"
                    }
                ],
                "doctor_name": "尚薇薇",
                "give_product_yn": 0,
                "yuyue_standard_str": "发起预约",
                "juli": ""
            }
        ],
        "product_info_other": [
            {
                "pid": "505698",
                "spu_id": "462292",
                "product_type": "2",
                "hospital_id": "107017",
                "total_cnt": 0,
                "sold_cnt": "15",
                "title": "【白瓷娃娃】【白瓷娃娃全面部】德国正版仪器/黄褐斑/祛斑/祛痘印/美白/嫩肤/收缩毛孔",
                "each_cnt": 0,
                "calendar_cnt": "1",
                "show_calendar_cnt": "30",
                "avg_score": "5.0",
                "marketing_language": "",
                "is_vip": "1",
                "is_vip_user": 0,
                "close_yn": "0",
                "display_yn": "1",
                "order_auto_cnt": "779",
                "order_cnt": 792,
                "price_online": "699",
                "price_deposit": "140",
                "price_origin": "1200",
                "paystages_notice": "首付预约金，尾款分期付：¥50.07 ×12期",
                "paystages_notice_android": "首付预约金，尾款分期付：<font color='#F57397'>¥50.07</font> ×12期",
                "wei_kuan_yn": 1,
                "wei_kuan": [
                    "100减10"
                ],
                "wei_kuan_list": [
                    "付尾款，最高立减¥10"
                ],
                "is_pin_tuan_yn": 0,
                "tuan": {
                    "product_tuan_id": "174361",
                    "pid": "505698",
                    "tuan_status_old": "1",
                    "tuan_status": 3,
                    "tuan_app_status": 0,
                    "product_tuan_price": "710",
                    "product_tuan_price_deposit": "142",
                    "product_tuan_price_hospital": 568,
                    "tuan_surplus_num": 0,
                    "tuan_product_cnt": "2",
                    "tuan_start_date": "2019-07-04 10:00:00",
                    "tuan_end_date": "2019-07-05 10:00:00",
                    "tuan_last_time": 0,
                    "tuan_product_num": "6",
                    "tuan_product_num_onsale": "6",
                    "tuan_mount": "1",
                    "product_tuan_time": "86400",
                    "tuan_topic_id": "9052"
                },
                "pin_tuan": [],
                "ori_on_sale_start_date": -62170012800,
                "ori_on_sale_end_date": -62170012800,
                "on_sale_flag": "0",
                "vip_user_on_sale": 0,
                "vip_cut": 21,
                "vip_price_online": "678",
                "vip_price_deposit": "119",
                "new_user_discount_price": 0,
                "new_user_discount_rate": 0,
                "new_user_text": "",
                "new_user_text_show_yn": 0,
                "price_cut": 0,
                "img_cover": {
                    "ident": "lnimage",
                    "w": "100",
                    "h": "100",
                    "u": "https://img2.soyoung.com/post/20191031/0/ab862d91434b67a1169afdfd9115b87c_400.png"
                },
                "gong_yn": "0",
                "bao_xian_yn": 0,
                "sole": "0",
                "security": "0",
                "tj_order": "0",
                "hospital_name": "北京杏林美医疗美容",
                "country": "2",
                "district_1": "1",
                "district_2": "1",
                "institution_type": "1",
                "paystages_notice_new": "首付预约金，尾款分期付：¥50.07 ×12期",
                "paystages_notice_android_new": "首付预约金，尾款分期付：<font color='#F57397'>¥50.07</font> ×12期",
                "subtitle": "",
                "product_icon_yn": 0,
                "product_icon": "",
                "doctor": [
                    {
                        "doctor_id": "157471",
                        "name_cn": "高春红",
                        "paystages": "0"
                    }
                ],
                "doctor_name": "高春红",
                "give_product_yn": 0,
                "yuyue_standard_str": "发起预约",
                "juli": ""
            },
            {
                "pid": "149780",
                "spu_id": "146956",
                "product_type": "2",
                "hospital_id": "658",
                "total_cnt": 0,
                "sold_cnt": "54",
                "title": "【美白导入】【韩国O₂氧动力】VC美白+动力补水+再生激光，一次解决皮肤多种问题！",
                "each_cnt": 0,
                "calendar_cnt": "0",
                "show_calendar_cnt": "0",
                "avg_score": "5.0",
                "marketing_language": "",
                "is_vip": "1",
                "is_vip_user": 0,
                "close_yn": "0",
                "display_yn": "1",
                "order_auto_cnt": "374",
                "order_cnt": 429,
                "price_online": "398",
                "price_deposit": "100",
                "price_origin": "980",
                "paystages_notice": "首付预约金，尾款分期付：¥26.69 ×12期",
                "paystages_notice_android": "首付预约金，尾款分期付：<font color='#F57397'>¥26.69</font> ×12期",
                "wei_kuan_yn": 1,
                "wei_kuan": [
                    "200减10"
                ],
                "wei_kuan_list": [
                    "付尾款，最高立减¥10"
                ],
                "is_pin_tuan_yn": 0,
                "tuan": {
                    "product_tuan_id": "100609",
                    "pid": "149780",
                    "tuan_status_old": "1",
                    "tuan_status": 3,
                    "tuan_app_status": 0,
                    "product_tuan_price": "279",
                    "product_tuan_price_deposit": "100",
                    "product_tuan_price_hospital": 179,
                    "tuan_surplus_num": 0,
                    "tuan_product_cnt": "2",
                    "tuan_start_date": "2019-05-24 11:00:00",
                    "tuan_end_date": "2019-06-07 10:59:00",
                    "tuan_last_time": 0,
                    "tuan_product_num": "10",
                    "tuan_product_num_onsale": "10",
                    "tuan_mount": "1",
                    "product_tuan_time": "172800",
                    "tuan_topic_id": "8388"
                },
                "pin_tuan": [],
                "ori_on_sale_start_date": -62170012800,
                "ori_on_sale_end_date": -62170012800,
                "on_sale_flag": "0",
                "vip_user_on_sale": 0,
                "vip_cut": 12,
                "vip_price_online": "386",
                "vip_price_deposit": "88",
                "new_user_discount_price": 0,
                "new_user_discount_rate": 0,
                "new_user_text": "",
                "new_user_text_show_yn": 0,
                "price_cut": 0,
                "img_cover": {
                    "ident": "lnimage",
                    "w": "100",
                    "h": "100",
                    "u": "https://img2.soyoung.com/post/20190927/9/85a7c4f4011e4aa0c7a22a1807aa4031_400.png"
                },
                "gong_yn": "0",
                "bao_xian_yn": 0,
                "sole": "0",
                "security": "0",
                "tj_order": "0",
                "hospital_name": "北京爱悦丽格医疗美容",
                "country": "2",
                "district_1": "1",
                "district_2": "1",
                "institution_type": "1",
                "paystages_notice_new": "首付预约金，尾款分期付：¥26.69 ×12期",
                "paystages_notice_android_new": "首付预约金，尾款分期付：<font color='#F57397'>¥26.69</font> ×12期",
                "subtitle": "",
                "doctor": [],
                "doctor_name": "",
                "give_product_yn": 0,
                "yuyue_standard_str": "发起预约",
                "juli": ""
            },
            {
                "pid": "424731",
                "spu_id": "395893",
                "product_type": "2",
                "hospital_id": "661",
                "total_cnt": 0,
                "sold_cnt": "14",
                "title": "【焕肤美白】【美肤套餐 】改善皮肤粗糙小米粒 温和去角质 加速皮肤代谢 靓白亮肤 均匀肤色",
                "each_cnt": 0,
                "calendar_cnt": "0",
                "show_calendar_cnt": "30",
                "avg_score": "5.0",
                "marketing_language": "",
                "is_vip": "0",
                "is_vip_user": 0,
                "close_yn": "0",
                "display_yn": "1",
                "order_auto_cnt": "526",
                "order_cnt": 538,
                "price_online": "398",
                "price_deposit": "100",
                "price_origin": "1280",
                "paystages_notice": "首付预约金，尾款分期付：¥26.69 ×12期",
                "paystages_notice_android": "首付预约金，尾款分期付：<font color='#F57397'>¥26.69</font> ×12期",
                "wei_kuan_yn": 1,
                "wei_kuan": [
                    "199减19"
                ],
                "wei_kuan_list": [
                    "付尾款，最高立减¥19"
                ],
                "is_pin_tuan_yn": 0,
                "tuan": {},
                "pin_tuan": [],
                "ori_on_sale_start_date": -62170012800,
                "ori_on_sale_end_date": -62170012800,
                "on_sale_flag": "0",
                "vip_user_on_sale": 0,
                "vip_cut": 0,
                "vip_price_online": "398",
                "vip_price_deposit": "100",
                "new_user_discount_price": 0,
                "new_user_discount_rate": 0,
                "new_user_text": "",
                "new_user_text_show_yn": 0,
                "price_cut": 0,
                "img_cover": {
                    "ident": "lnimage",
                    "w": "100",
                    "h": "100",
                    "u": "https://img2.soyoung.com/post/20191116/7/4979146570c7371270277c1de98a248f_400.jpg"
                },
                "gong_yn": "0",
                "bao_xian_yn": 0,
                "sole": "0",
                "security": "0",
                "tj_order": "0",
                "hospital_name": "北京伟力嘉美信医疗美容",
                "country": "2",
                "district_1": "1",
                "district_2": "1",
                "institution_type": "1",
                "paystages_notice_new": "首付预约金，尾款分期付：¥26.69 ×12期",
                "paystages_notice_android_new": "首付预约金，尾款分期付：<font color='#F57397'>¥26.69</font> ×12期",
                "subtitle": "",
                "doctor": [
                    {
                        "doctor_id": "147414",
                        "name_cn": "陈文辉",
                        "paystages": "0"
                    }
                ],
                "doctor_name": "陈文辉",
                "give_product_yn": 0,
                "yuyue_standard_str": "发起预约",
                "juli": ""
            },
            {
                "pid": "206452",
                "spu_id": "202425",
                "product_type": "2",
                "hospital_id": "26469",
                "total_cnt": 0,
                "sold_cnt": "58",
                "title": "【彩光嫩肤】【以色列飞顿光子嫩肤】IPL光子嫩肤，美白，晒后修复，抗光老化，淡斑，祛红",
                "each_cnt": 0,
                "calendar_cnt": "0",
                "show_calendar_cnt": "30",
                "avg_score": "5.0",
                "marketing_language": "",
                "is_vip": "1",
                "is_vip_user": 0,
                "close_yn": "0",
                "display_yn": "1",
                "order_auto_cnt": "508",
                "order_cnt": 574,
                "price_online": "376",
                "price_deposit": "100",
                "price_origin": "2280",
                "paystages_notice": "",
                "paystages_notice_android": "",
                "wei_kuan_yn": 0,
                "wei_kuan": [],
                "wei_kuan_list": [],
                "is_pin_tuan_yn": 0,
                "tuan": {},
                "pin_tuan": [],
                "ori_on_sale_start_date": -62170012800,
                "ori_on_sale_end_date": -62170012800,
                "on_sale_flag": "0",
                "vip_user_on_sale": 0,
                "vip_cut": 11,
                "vip_price_online": "365",
                "vip_price_deposit": "89",
                "new_user_discount_price": 0,
                "new_user_discount_rate": 0,
                "new_user_text": "",
                "new_user_text_show_yn": 0,
                "price_cut": 0,
                "img_cover": {
                    "ident": "lnimage",
                    "w": "100",
                    "h": "100",
                    "u": "https://img2.soyoung.com/post/20191119/6/92089ea1a7f0631f7eda7fa383ed23bc_400.png"
                },
                "gong_yn": "0",
                "bao_xian_yn": 0,
                "sole": "0",
                "security": "0",
                "tj_order": "0",
                "hospital_name": "北京华韩医疗美容医院",
                "country": "2",
                "district_1": "1",
                "district_2": "1",
                "institution_type": "1",
                "subtitle": "",
                "product_icon_yn": 0,
                "product_icon": "",
                "doctor": [
                    {
                        "doctor_id": "142602",
                        "name_cn": "邢志花",
                        "paystages": "0"
                    },
                    {
                        "doctor_id": "155746",
                        "name_cn": "高春雪",
                        "paystages": "0"
                    }
                ],
                "doctor_name": "邢志花",
                "give_product_yn": 0,
                "yuyue_standard_str": "发起预约",
                "juli": ""
            },
            {
                "pid": "582363",
                "spu_id": "526333",
                "product_type": "2",
                "hospital_id": "632",
                "total_cnt": 0,
                "sold_cnt": "0",
                "title": "【玻尿酸导入】【补水美白修复套餐】 补水/美白/嫩肤/晒后修复/平衡肌理",
                "each_cnt": 0,
                "calendar_cnt": "0",
                "show_calendar_cnt": "13",
                "avg_score": "0.0",
                "marketing_language": "",
                "is_vip": "1",
                "is_vip_user": 0,
                "close_yn": "0",
                "display_yn": "1",
                "order_auto_cnt": "60",
                "order_cnt": 60,
                "price_online": "399",
                "price_deposit": "100",
                "price_origin": "799",
                "paystages_notice": "首付预约金，尾款分期付：¥26.77 ×12期",
                "paystages_notice_android": "首付预约金，尾款分期付：<font color='#F57397'>¥26.77</font> ×12期",
                "wei_kuan_yn": 0,
                "wei_kuan": [],
                "wei_kuan_list": [],
                "is_pin_tuan_yn": 0,
                "tuan": {},
                "pin_tuan": [],
                "ori_on_sale_start_date": -62170012800,
                "ori_on_sale_end_date": -62170012800,
                "on_sale_flag": "0",
                "vip_user_on_sale": 0,
                "vip_cut": 12,
                "vip_price_online": "387",
                "vip_price_deposit": "88",
                "new_user_discount_price": 0,
                "new_user_discount_rate": 0,
                "new_user_text": "",
                "new_user_text_show_yn": 0,
                "price_cut": 0,
                "img_cover": {
                    "ident": "lnimage",
                    "w": "100",
                    "h": "100",
                    "u": "https://img2.soyoung.com/post/20191119/0/8865c0008b92f951359a8456eb9f6a3c_400.png"
                },
                "gong_yn": "0",
                "bao_xian_yn": 0,
                "sole": "0",
                "security": "0",
                "tj_order": "0",
                "hospital_name": "俊泰丽格医疗美容",
                "country": "2",
                "district_1": "1",
                "district_2": "1",
                "institution_type": "1",
                "paystages_notice_new": "首付预约金，尾款分期付：¥26.77 ×12期",
                "paystages_notice_android_new": "首付预约金，尾款分期付：<font color='#F57397'>¥26.77</font> ×12期",
                "subtitle": "",
                "doctor": [
                    {
                        "doctor_id": "156194",
                        "name_cn": "邓立育",
                        "paystages": "0"
                    }
                ],
                "doctor_name": "邓立育",
                "give_product_yn": 0,
                "yuyue_standard_str": "发起预约",
                "juli": ""
            },
            {
                "pid": "103621",
                "spu_id": "100931",
                "product_type": "2",
                "hospital_id": "23303",
                "total_cnt": 0,
                "sold_cnt": "18",
                "title": "【焕肤美白】飞顿NIR美白牛奶光 美白淡斑 紧肤除皱 改善肤色 胶原再生 肌肤水嫩白皙限购1",
                "each_cnt": 0,
                "calendar_cnt": "2",
                "show_calendar_cnt": "30",
                "avg_score": "4.5",
                "marketing_language": "",
                "is_vip": "1",
                "is_vip_user": 0,
                "close_yn": "0",
                "display_yn": "1",
                "order_auto_cnt": "427",
                "order_cnt": 884,
                "price_online": "198",
                "price_deposit": "100",
                "price_origin": "28000",
                "paystages_notice": "首付预约金，尾款分期付：¥8.77 ×12期",
                "paystages_notice_android": "首付预约金，尾款分期付：<font color='#F57397'>¥8.77</font> ×12期",
                "wei_kuan_yn": 1,
                "wei_kuan": [
                    "100减5",
                    "100减5"
                ],
                "wei_kuan_list": [
                    "付尾款，最高立减¥5",
                    "付尾款，最高立减¥5"
                ],
                "is_pin_tuan_yn": 0,
                "tuan": {},
                "pin_tuan": [],
                "ori_on_sale_start_date": -62170012800,
                "ori_on_sale_end_date": -62170012800,
                "on_sale_flag": "0",
                "vip_user_on_sale": 0,
                "vip_cut": 6,
                "vip_price_online": "192",
                "vip_price_deposit": "94",
                "new_user_discount_price": 0,
                "new_user_discount_rate": 0,
                "new_user_text": "",
                "new_user_text_show_yn": 0,
                "price_cut": 0,
                "img_cover": {
                    "ident": "lnimage",
                    "w": "100",
                    "h": "100",
                    "u": "https://img2.soyoung.com/post/20191023/0/cf541990bfea36b0f1046414a86bdb11_400.png"
                },
                "gong_yn": "0",
                "bao_xian_yn": 0,
                "sole": "0",
                "security": "0",
                "tj_order": "0",
                "hospital_name": "北京雅靓医疗美容",
                "country": "2",
                "district_1": "1",
                "district_2": "1",
                "institution_type": "1",
                "paystages_notice_new": "首付预约金，尾款分期付：¥8.77 ×12期",
                "paystages_notice_android_new": "首付预约金，尾款分期付：<font color='#F57397'>¥8.77</font> ×12期",
                "subtitle": "",
                "product_icon_yn": 0,
                "product_icon": "",
                "doctor": [
                    {
                        "doctor_id": "78988",
                        "name_cn": "张春彦",
                        "paystages": "0"
                    }
                ],
                "doctor_name": "张春彦",
                "give_product_yn": 0,
                "yuyue_standard_str": "发起预约",
                "juli": ""
            },
            {
                "pid": "768",
                "spu_id": "776",
                "product_type": "2",
                "hospital_id": "661",
                "total_cnt": 0,
                "sold_cnt": "113",
                "title": "【黑脸娃娃】【低价尊享】黑脸娃娃/白瓷娃娃二选一 祛黄褐斑 除黄气暗黄毛孔粗大  美白肌肤 ",
                "each_cnt": 0,
                "calendar_cnt": "18",
                "show_calendar_cnt": "30",
                "avg_score": "5.0",
                "marketing_language": "",
                "is_vip": "1",
                "is_vip_user": 0,
                "close_yn": "0",
                "display_yn": "1",
                "order_auto_cnt": "1143",
                "order_cnt": 1270,
                "price_online": "380",
                "price_deposit": "100",
                "price_origin": "2580",
                "paystages_notice": "首付预约金，尾款分期付：¥25.08 ×12期",
                "paystages_notice_android": "首付预约金，尾款分期付：<font color='#F57397'>¥25.08</font> ×12期",
                "wei_kuan_yn": 1,
                "wei_kuan": [
                    "199减19"
                ],
                "wei_kuan_list": [
                    "付尾款，最高立减¥19"
                ],
                "is_pin_tuan_yn": 0,
                "tuan": {
                    "product_tuan_id": "206380",
                    "pid": "768",
                    "tuan_status_old": "1",
                    "tuan_status": 3,
                    "tuan_app_status": 0,
                    "product_tuan_price": "190",
                    "product_tuan_price_deposit": "100",
                    "product_tuan_price_hospital": 90,
                    "tuan_surplus_num": 0,
                    "tuan_product_cnt": "2",
                    "tuan_start_date": "2019-08-09 10:00:00",
                    "tuan_end_date": "2019-08-16 10:00:00",
                    "tuan_last_time": 0,
                    "tuan_product_num": "32",
                    "tuan_product_num_onsale": "30",
                    "tuan_mount": "99",
                    "product_tuan_time": "86400",
                    "tuan_topic_id": "999999999"
                },
                "pin_tuan": [],
                "ori_on_sale_start_date": 1574611200,
                "ori_on_sale_end_date": 1575129599,
                "on_sale_flag": "1",
                "vip_user_on_sale": 0,
                "vip_cut": 11,
                "vip_price_online": "369",
                "vip_price_deposit": "89",
                "new_user_discount_price": 0,
                "new_user_discount_rate": 0,
                "new_user_text": "",
                "new_user_text_show_yn": 0,
                "price_cut": 0,
                "img_cover": {
                    "ident": "lnimage",
                    "w": "100",
                    "h": "100",
                    "u": "https://img2.soyoung.com/post/20191116/5/1df61f005bdff8608c9511e7bc4cd6fc_400.jpg"
                },
                "gong_yn": "0",
                "bao_xian_yn": 0,
                "sole": "0",
                "security": "0",
                "tj_order": "0",
                "hospital_name": "北京伟力嘉美信医疗美容",
                "country": "2",
                "district_1": "1",
                "district_2": "1",
                "institution_type": "1",
                "paystages_notice_new": "首付预约金，尾款分期付：¥25.08 ×12期",
                "paystages_notice_android_new": "首付预约金，尾款分期付：<font color='#F57397'>¥25.08</font> ×12期",
                "subtitle": "",
                "product_icon_yn": 0,
                "product_icon": "",
                "doctor": [
                    {
                        "doctor_id": "147414",
                        "name_cn": "陈文辉",
                        "paystages": "0"
                    }
                ],
                "doctor_name": "陈文辉",
                "give_product_yn": 0,
                "yuyue_standard_str": "发起预约",
                "juli": ""
            },
            {
                "pid": "294911",
                "spu_id": "284668",
                "product_type": "2",
                "hospital_id": "103128",
                "total_cnt": "5",
                "sold_cnt": "0",
                "title": "【美白针】【名医给你还花呗】【韩国直营】【全身美白10次】【皮肤黑真的丑】秒变白富美",
                "each_cnt": "0",
                "calendar_cnt": "7",
                "show_calendar_cnt": "30",
                "avg_score": "4.9",
                "marketing_language": "",
                "is_vip": "1",
                "is_vip_user": 0,
                "close_yn": "0",
                "display_yn": "1",
                "order_auto_cnt": "865",
                "order_cnt": 1209,
                "price_online": "1998",
                "price_deposit": "400",
                "price_origin": "2498",
                "paystages_notice": "首付预约金，尾款分期付：¥143.14 ×12期",
                "paystages_notice_android": "首付预约金，尾款分期付：<font color='#F57397'>¥143.14</font> ×12期",
                "wei_kuan_yn": 0,
                "wei_kuan": [],
                "wei_kuan_list": [],
                "is_pin_tuan_yn": 0,
                "tuan": {
                    "product_tuan_id": "202521",
                    "pid": "294911",
                    "tuan_status_old": "1",
                    "tuan_status": 3,
                    "tuan_app_status": 0,
                    "product_tuan_price": "398",
                    "product_tuan_price_deposit": "100",
                    "product_tuan_price_hospital": 298,
                    "tuan_surplus_num": 0,
                    "tuan_product_cnt": "2",
                    "tuan_start_date": "2019-07-19 10:00:00",
                    "tuan_end_date": "2019-07-26 10:00:00",
                    "tuan_last_time": 0,
                    "tuan_product_num": "32",
                    "tuan_product_num_onsale": "32",
                    "tuan_mount": "1",
                    "product_tuan_time": "86400",
                    "tuan_topic_id": "999999999"
                },
                "pin_tuan": [],
                "ori_on_sale_start_date": 1574391600,
                "ori_on_sale_end_date": 1574820000,
                "on_sale_flag": "1",
                "vip_user_on_sale": "0",
                "last_cnt_type": 1,
                "purchlimit_yn": 1,
                "purchlimit_type": "1",
                "on_sale_start_date": 1574391600,
                "on_sale_end_date": 1574820000,
                "purchlimit_endtime": 1574820000,
                "purchlimit_text": "活动结束后恢复¥2498，仅剩5个",
                "vip_cut": 60,
                "vip_price_online": "1938",
                "vip_price_deposit": "340",
                "new_user_discount_price": 0,
                "new_user_discount_rate": 0,
                "new_user_text": "",
                "new_user_text_show_yn": 0,
                "price_cut": 500,
                "img_cover": {
                    "ident": "lnimage",
                    "w": "100",
                    "h": "100",
                    "u": "https://img2.soyoung.com/post/20191116/0/8a0a1a2ee98ed306bd0ba339a404c4fd_400.png"
                },
                "gong_yn": "0",
                "bao_xian_yn": 0,
                "sole": "0",
                "security": "0",
                "tj_order": "0",
                "hospital_name": "爱慕医疗美容",
                "country": "2",
                "district_1": "1",
                "district_2": "1",
                "institution_type": "1",
                "paystages_notice_new": "首付预约金，尾款分期付：¥143.14 ×12期",
                "paystages_notice_android_new": "首付预约金，尾款分期付：<font color='#F57397'>¥143.14</font> ×12期",
                "subtitle": "",
                "doctor": [
                    {
                        "doctor_id": "147323",
                        "name_cn": "张曼",
                        "paystages": "0"
                    }
                ],
                "doctor_name": "张曼",
                "give_product_yn": 0,
                "yuyue_standard_str": "发起预约",
                "juli": ""
            },
            {
                "pid": "546637",
                "spu_id": "496146",
                "product_type": "2",
                "hospital_id": "7974",
                "total_cnt": 0,
                "sold_cnt": "9",
                "title": "【美白针】【全身美白】【静脉注射】【美白淡斑】【疗程卡10次】订制你的专属美白计划。",
                "each_cnt": 0,
                "calendar_cnt": "0",
                "show_calendar_cnt": "30",
                "avg_score": "5.0",
                "marketing_language": "",
                "is_vip": "1",
                "is_vip_user": 0,
                "close_yn": "0",
                "display_yn": "1",
                "order_auto_cnt": "31",
                "order_cnt": 41,
                "price_online": "2580",
                "price_deposit": "516",
                "price_origin": "5580",
                "paystages_notice": "首付预约金，尾款分期付：¥184.9 ×12期",
                "paystages_notice_android": "首付预约金，尾款分期付：<font color='#F57397'>¥184.9</font> ×12期",
                "wei_kuan_yn": 0,
                "wei_kuan": [],
                "wei_kuan_list": [],
                "is_pin_tuan_yn": 0,
                "tuan": {},
                "pin_tuan": [],
                "ori_on_sale_start_date": -62170012800,
                "ori_on_sale_end_date": -62170012800,
                "on_sale_flag": "0",
                "vip_user_on_sale": 0,
                "vip_cut": 77,
                "vip_price_online": "2503",
                "vip_price_deposit": "439",
                "new_user_discount_price": 0,
                "new_user_discount_rate": 0,
                "new_user_text": "",
                "new_user_text_show_yn": 0,
                "price_cut": 0,
                "img_cover": {
                    "ident": "lnimage",
                    "w": "100",
                    "h": "100",
                    "u": "https://img2.soyoung.com/post/20190826/0/2874f38f6e5a30717cf5fa52916dc169_400.png"
                },
                "gong_yn": "0",
                "bao_xian_yn": 0,
                "sole": "0",
                "security": "0",
                "tj_order": "0",
                "hospital_name": "北京金圣整形医疗美容",
                "country": "2",
                "district_1": "1",
                "district_2": "1",
                "institution_type": "1",
                "paystages_notice_new": "首付预约金，尾款分期付：¥184.9 ×12期",
                "paystages_notice_android_new": "首付预约金，尾款分期付：<font color='#F57397'>¥184.9</font> ×12期",
                "subtitle": "",
                "doctor": [
                    {
                        "doctor_id": "37496",
                        "name_cn": "辛晴",
                        "paystages": "0"
                    }
                ],
                "doctor_name": "辛晴",
                "give_product_yn": 0,
                "yuyue_standard_str": "发起预约",
                "juli": ""
            },
            {
                "pid": "580968",
                "spu_id": "525180",
                "product_type": "2",
                "hospital_id": "4669",
                "total_cnt": "5",
                "sold_cnt": "0",
                "title": "【玻尿酸导入】玻尿酸补水导入 美白嫩肤 补水加速 让肌肤活起来",
                "each_cnt": "1",
                "calendar_cnt": "0",
                "show_calendar_cnt": "5",
                "avg_score": "5.0",
                "marketing_language": "",
                "is_vip": "1",
                "is_vip_user": 0,
                "close_yn": "0",
                "display_yn": "1",
                "order_auto_cnt": "35",
                "order_cnt": 36,
                "price_online": "150",
                "price_deposit": "100",
                "price_origin": "188",
                "paystages_notice": "首付预约金，尾款分期付：¥3.12 ×12期",
                "paystages_notice_android": "首付预约金，尾款分期付：<font color='#F57397'>¥3.12</font> ×12期",
                "wei_kuan_yn": 0,
                "wei_kuan": [],
                "wei_kuan_list": [],
                "is_pin_tuan_yn": 0,
                "tuan": {},
                "pin_tuan": [],
                "ori_on_sale_start_date": 1574391600,
                "ori_on_sale_end_date": 1574820000,
                "on_sale_flag": "1",
                "vip_user_on_sale": "0",
                "last_cnt_type": 1,
                "purchlimit_yn": 1,
                "purchlimit_type": "1",
                "on_sale_start_date": 1574391600,
                "on_sale_end_date": 1574820000,
                "purchlimit_endtime": 1574820000,
                "purchlimit_text": "活动结束后恢复¥188，仅剩5个",
                "vip_cut": 4,
                "vip_price_online": "146",
                "vip_price_deposit": "96",
                "new_user_discount_price": 15,
                "new_user_discount_rate": "90",
                "new_user_text": "新人首单立减¥15",
                "new_user_text_show_yn": 1,
                "price_cut": 38,
                "img_cover": {
                    "ident": "lnimage",
                    "w": "100",
                    "h": "100",
                    "u": "https://img2.soyoung.com/post/20191114/5/98056b4ab312fa8f7c9ce006286a5fe8_400.png"
                },
                "gong_yn": "0",
                "bao_xian_yn": 0,
                "sole": "0",
                "security": "0",
                "tj_order": "0",
                "hospital_name": "北京中加科洋美容整形",
                "country": "2",
                "district_1": "1",
                "district_2": "1",
                "institution_type": "1",
                "paystages_notice_new": "首付预约金，尾款分期付：¥3.12 ×12期",
                "paystages_notice_android_new": "首付预约金，尾款分期付：<font color='#F57397'>¥3.12</font> ×12期",
                "subtitle": "",
                "doctor": [
                    {
                        "doctor_id": "81612",
                        "name_cn": "万燕子",
                        "paystages": "0"
                    }
                ],
                "doctor_name": "万燕子",
                "give_product_yn": 0,
                "yuyue_standard_str": "发起预约",
                "juli": ""
            },
            {
                "pid": "555545",
                "spu_id": "503606",
                "product_type": "2",
                "hospital_id": "21987",
                "total_cnt": "7",
                "sold_cnt": "1",
                "title": "【白瓷娃娃】【正品C6仪器/白瓷娃娃】美白嫩肤 提亮肤色 去黄去暗沉",
                "each_cnt": "1",
                "calendar_cnt": "0",
                "show_calendar_cnt": "30",
                "avg_score": "5.0",
                "marketing_language": "",
                "is_vip": "1",
                "is_vip_user": 0,
                "close_yn": "0",
                "display_yn": "1",
                "order_auto_cnt": "80",
                "order_cnt": 100,
                "price_online": "405",
                "price_deposit": "100",
                "price_origin": "810",
                "paystages_notice": "首付预约金，尾款分期付：¥27.31 ×12期",
                "paystages_notice_android": "首付预约金，尾款分期付：<font color='#F57397'>¥27.31</font> ×12期",
                "wei_kuan_yn": 0,
                "wei_kuan": [],
                "wei_kuan_list": [],
                "is_pin_tuan_yn": 0,
                "tuan": {},
                "pin_tuan": [],
                "ori_on_sale_start_date": 1574128800,
                "ori_on_sale_end_date": 1574733600,
                "on_sale_flag": "1",
                "vip_user_on_sale": "0",
                "last_cnt_type": 1,
                "purchlimit_yn": 1,
                "purchlimit_type": "1",
                "on_sale_start_date": 1574128800,
                "on_sale_end_date": 1574733600,
                "purchlimit_endtime": 1574733600,
                "purchlimit_text": "活动结束后恢复¥810，仅剩6个",
                "vip_cut": 12,
                "vip_price_online": "393",
                "vip_price_deposit": "88",
                "new_user_discount_price": 0,
                "new_user_discount_rate": 0,
                "new_user_text": "",
                "new_user_text_show_yn": 0,
                "price_cut": 405,
                "img_cover": {
                    "ident": "lnimage",
                    "w": "100",
                    "h": "100",
                    "u": "https://img2.soyoung.com/post/20191017/7/368531a6a54b62f04b858e9b4ef30e5e_400.png"
                },
                "gong_yn": "0",
                "bao_xian_yn": 0,
                "sole": "0",
                "security": "0",
                "tj_order": "0",
                "hospital_name": "北京焕誉医疗美容门诊部",
                "country": "2",
                "district_1": "1",
                "district_2": "1",
                "institution_type": "1",
                "paystages_notice_new": "首付预约金，尾款分期付：¥27.31 ×12期",
                "paystages_notice_android_new": "首付预约金，尾款分期付：<font color='#F57397'>¥27.31</font> ×12期",
                "subtitle": "",
                "doctor": [
                    {
                        "doctor_id": "159330",
                        "name_cn": "黄宇青",
                        "paystages": "0"
                    }
                ],
                "doctor_name": "黄宇青",
                "give_product_yn": 0,
                "yuyue_standard_str": "发起预约",
                "juli": ""
            },
            {
                "pid": "80114",
                "spu_id": "77515",
                "product_type": "2",
                "hospital_id": "23581",
                "total_cnt": "11",
                "sold_cnt": "1",
                "title": "【白瓷娃娃】白瓷娃娃 美白嫩肤 祛斑无瑕  打造Q弹肌肤 到店有好礼",
                "each_cnt": "1",
                "calendar_cnt": "5",
                "show_calendar_cnt": "30",
                "avg_score": "4.9",
                "marketing_language": "",
                "is_vip": "1",
                "is_vip_user": 0,
                "close_yn": "0",
                "display_yn": "1",
                "order_auto_cnt": "535",
                "order_cnt": 759,
                "price_online": "129",
                "price_deposit": "100",
                "price_origin": "258",
                "paystages_notice": "首付预约金，尾款分期付：¥2.59 ×12期",
                "paystages_notice_android": "首付预约金，尾款分期付：<font color='#F57397'>¥2.59</font> ×12期",
                "wei_kuan_yn": 0,
                "wei_kuan": [],
                "wei_kuan_list": [],
                "is_pin_tuan_yn": 0,
                "tuan": {
                    "product_tuan_id": "215538",
                    "pid": "80114",
                    "tuan_status_old": "1",
                    "tuan_status": 3,
                    "tuan_app_status": 0,
                    "product_tuan_price": "181",
                    "product_tuan_price_deposit": "100",
                    "product_tuan_price_hospital": 81,
                    "tuan_surplus_num": 0,
                    "tuan_product_cnt": "2",
                    "tuan_start_date": "2019-10-16 11:00:00",
                    "tuan_end_date": "2019-10-21 10:00:00",
                    "tuan_last_time": 0,
                    "tuan_product_num": "50",
                    "tuan_product_num_onsale": "50",
                    "tuan_mount": "99",
                    "product_tuan_time": "86400",
                    "tuan_topic_id": "999999999"
                },
                "pin_tuan": [],
                "ori_on_sale_start_date": 1574128800,
                "ori_on_sale_end_date": 1574733600,
                "on_sale_flag": "1",
                "vip_user_on_sale": "0",
                "last_cnt_type": 1,
                "purchlimit_yn": 1,
                "purchlimit_type": "1",
                "on_sale_start_date": 1574128800,
                "on_sale_end_date": 1574733600,
                "purchlimit_endtime": 1574733600,
                "purchlimit_text": "活动结束后恢复¥258，仅剩10个",
                "vip_cut": 4,
                "vip_price_online": "125",
                "vip_price_deposit": "96",
                "new_user_discount_price": 0,
                "new_user_discount_rate": 0,
                "new_user_text": "",
                "new_user_text_show_yn": 0,
                "price_cut": 129,
                "img_cover": {
                    "ident": "lnimage",
                    "w": "100",
                    "h": "100",
                    "u": "https://img2.soyoung.com/post/20191114/9/907091917c4a07fa59644b7fa767b476_400.png"
                },
                "gong_yn": "0",
                "bao_xian_yn": 0,
                "sole": "0",
                "security": "0",
                "tj_order": "0",
                "hospital_name": "唯颜时代医疗美容诊所",
                "country": "2",
                "district_1": "1",
                "district_2": "1",
                "institution_type": "1",
                "paystages_notice_new": "首付预约金，尾款分期付：¥2.59 ×12期",
                "paystages_notice_android_new": "首付预约金，尾款分期付：<font color='#F57397'>¥2.59</font> ×12期",
                "subtitle": "补水 嫩肤 美白",
                "product_icon_yn": 0,
                "product_icon": "",
                "doctor": [
                    {
                        "doctor_id": "54754",
                        "name_cn": "张总其",
                        "paystages": "0"
                    }
                ],
                "doctor_name": "张总其",
                "give_product_yn": 0,
                "yuyue_standard_str": "发起预约",
                "juli": ""
            }
        ]

    }
}